stack_bot/__init__.py
stack_bot/src/database_base/__init__.py
stack_bot/src/database_base/driver.py
stack_bot/src/database_base/table.py
stack_bot/src/database_base/table_decorator.py
stack_bot/src/database_base/table_row.py
stack_bot/src/elements/__init__.py
stack_bot/src/elements/api_elements.py
stack_bot/src/elements/bot_elements.py
stack_bot/src/init/__init__.py
stack_bot/src/init/init.py
stack_bot/src/init/manager.py
stack_bot/src/state_base/__init__.py
stack_bot/src/state_base/impl.py
stack_bot/src/state_base/state.py
stack_bot/src/state_base/state_bot.py
stack_bot/src/state_base/telegrambot.py
stack_bot/src/utils/__init__.py
stack_bot/src/utils/utils.py
stack_bot-0.2.0.dist-info/METADATA
stack_bot-0.2.0.dist-info/WHEEL
stack_bot-0.2.0.dist-info/top_level.txt
stack_bot-0.2.0.dist-info/RECORD
